DependencySolver/__init__.py
DependencySolver/_version.py
DependencySolver/run.py
DependencySolver/solver.py
DependencySolver/sort_ordering.py
DependencySolver/ui.py
DependencySolver/ui_canvas.py
DependencySolver/ui_treeview.py
robotframework_dependencysolver-1.2.1.dist-info/licenses/LICENSE
robotframework_dependencysolver-1.2.1.dist-info/METADATA
robotframework_dependencysolver-1.2.1.dist-info/WHEEL
robotframework_dependencysolver-1.2.1.dist-info/entry_points.txt
robotframework_dependencysolver-1.2.1.dist-info/top_level.txt
robotframework_dependencysolver-1.2.1.dist-info/RECORD
