Metadata-Version: 2.4
Name: robotframework-dependencysolver
Version: 1.2.1
Summary: A Robot Framework prerunmodifier for interdependent test cases execution.
Author-email: Joonas Kuisma <kuisma.joonas@gmail.com>
License:                                  Apache License
Project-URL: Homepage, https://github.com/joonaskuisma/robotframework-dependencysolver
Project-URL: Issues, https://github.com/joonaskuisma/robotframework-dependencysolver/issues
Project-URL: Download, https://pypi.org/project/robotframework-dependencysolver/
Keywords: robotframework,dependencysolver,dependencylibrary,prerunmodifier, testautomation
Classifier: Development Status :: 5 - Production/Stable
Classifier: Intended Audience :: Developers
Classifier: Topic :: Software Development :: Testing
Classifier: Framework :: Robot Framework :: Library
Classifier: License :: OSI Approved :: Apache Software License
Classifier: Programming Language :: Python :: 3
Classifier: Operating System :: OS Independent
Requires-Python: >=3.10
License-File: LICENSE
Requires-Dist: robotframework>=5.0
Requires-Dist: robotframework-dependencylibrary>=4.0
Provides-Extra: dev
Requires-Dist: pytest; extra == "dev"
Requires-Dist: pytest-cov; extra == "dev"
Requires-Dist: robotframework-pabot>=4.1; extra == "dev"
Provides-Extra: pabot
Requires-Dist: robotframework-pabot>=4.1; extra == "pabot"
Dynamic: license-file
